LICENSE
MANIFEST.in
Makefile
README
setup.py
test/test_compile.py
test/test_filters.py
tiddlywebplugins/__init__.py
tiddlywebplugins/templates.py
tiddlywebplugins.templates.egg-info/PKG-INFO
tiddlywebplugins.templates.egg-info/SOURCES.txt
tiddlywebplugins.templates.egg-info/dependency_links.txt
tiddlywebplugins.templates.egg-info/namespace_packages.txt
tiddlywebplugins.templates.egg-info/not-zip-safe
tiddlywebplugins.templates.egg-info/pbr.json
tiddlywebplugins.templates.egg-info/requires.txt
tiddlywebplugins.templates.egg-info/top_level.txt
tiddlywebplugins/templates/null.html