Metadata-Version: 1.0
Name: tiddlywebplugins.templates
Version: 0.9.7
Summary: A TiddlyWeb plugin with tools and packaging for templates.
Home-page: http://pypi.python.org/pypi/tiddlywebplugins.templates
Author: Chris Dent
Author-email: cdent@peermore.com
License: BSD
Platform: Posix; MacOS X; Windows
